Metadata-Version: 2.1
Name: flisol-example-package
Version: 0.0.0
Summary: FLISol Example Package
Home-page: https://gitlab.com/ettoreleandrotognoli/pypi-flisol
Author: Ettore Leandro Tognoli
Author-email: ettoreleandrotognoli@gmail.com
License: MIT
Platform: UNKNOWN
Classifier: License :: OSI Approved :: MIT License
